pesapal_py/__init__.py
pesapal_py/payments.py
pesapal_py-0.1.3.dist-info/LICENSE.md
pesapal_py-0.1.3.dist-info/METADATA
pesapal_py-0.1.3.dist-info/WHEEL
pesapal_py-0.1.3.dist-info/top_level.txt
pesapal_py-0.1.3.dist-info/RECORD
