Metadata-Version: 2.1
Name: pesapal-py
Version: 0.1.3
Summary: A minimalist python library that integrates with PesaPal's API 3.0 - JSON APIs (https://developer.pesapal.com/how-to-integrate/e-commerce/api-30-json/api-reference)
Home-page: https://github.com/twais/pesapal-py
Download-URL: https://github.com/twais/pesapal-py/archive/refs/tags/v0.0.1.tar.gz
Author: Brian Owino Otieno
Author-email: brian.otieno709@gmail.com
License-File: LICENSE.md
Requires-Dist: requests
